{
  "project_info": {
    "project_number": "22327455704",
    "project_id": "studybuddy-4187f",
    "storage_bucket": "studybuddy-4187f.firebasestorage.app"
  },
  "client": [
    {
      "client_info": {
        "mobilesdk_app_id": "1:22327455704:android:65488fd608fc3e535d8cad",
        "android_client_info": {
          "package_name": "com.studybuddymobile"
        }
      },
      "oauth_client": [],
      "api_key": [
        {
          "current_key": "AIzaSyAd7KX1A5UjV8n9MOTpf8qcSo7H5l_BG_w"
        }
      ],
      "services": {
        "appinvite_service": {
          "other_platform_oauth_client": []
        }
      }
    }
  ],
  "configuration_version": "1"
}